README.md
setup.cfg
setup.py
LibBinTViewVariable/Binance.py
LibBinTViewVariable/Elastic.py
LibBinTViewVariable/General.py
LibBinTViewVariable/RabbitMQ.py
LibBinTViewVariable/TradingView.py
LibBinTViewVariable/__init__.py
LibBinTViewVariable.egg-info/PKG-INFO
LibBinTViewVariable.egg-info/SOURCES.txt
LibBinTViewVariable.egg-info/dependency_links.txt
LibBinTViewVariable.egg-info/top_level.txt