Metadata-Version: 2.1
Name: LibBinTViewVariable
Version: 0.1.4.7.5
Summary: A package to share constants from Binance and TradingView
Home-page: https://github.com/Vankezzz/BinTViewVariable/
Author: Yonas Guryavichyus
Author-email: yagur1998@gmail.com
License: UNKNOWN
Platform: UNKNOWN
Classifier: Programming Language :: Python :: 3.9
Classifier: License :: OSI Approved :: GNU General Public License v3 (GPLv3)
